seyhuns_bencode/__init__.py
seyhuns_bencode/__main__.py
seyhuns_bencode/__version__.py
seyhuns_bencode/bencode.py
seyhuns_bencode/exceptions.py
seyhuns_bencode-0.1.6.dist-info/LICENSE.md
seyhuns_bencode-0.1.6.dist-info/METADATA
seyhuns_bencode-0.1.6.dist-info/WHEEL
seyhuns_bencode-0.1.6.dist-info/entry_points.txt
seyhuns_bencode-0.1.6.dist-info/top_level.txt
seyhuns_bencode-0.1.6.dist-info/RECORD
