Metadata-Version: 2.1
Name: seyhuns-bencode
Version: 0.1.6
Summary: Bencode Parser
Home-page: https://github.com/seyhuns/bencode
Author: Rustu Seyhun Sariyildiz
Author-email: me@seyhun.dev
License: MIT
Platform: UNKNOWN
Classifier: License :: OSI Approved :: MIT License
Classifier: Programming Language :: Python
Classifier: Programming Language :: Python :: 3
Classifier: Programming Language :: Python :: 3.7
Classifier: Programming Language :: Python :: Implementation :: CPython
Classifier: Programming Language :: Python :: Implementation :: PyPy
Requires-Python: >=3.7.0
Requires-Dist: docopt
Requires-Dist: requests
